chsu_schedule_api/__init__.py
chsu_schedule_api/api/__init__.py
chsu_schedule_api/api/abc.py
chsu_schedule_api/api/api.py
chsu_schedule_api/client/__init__.py
chsu_schedule_api/client/abc.py
chsu_schedule_api/client/aiohttp.py
chsu_schedule_api/constants.py
chsu_schedule_api/enums.py
chsu_schedule_api/errors.py
chsu_schedule_api/sync.py
chsu_schedule_api/types/__init__.py
chsu_schedule_api/types/auditorium.py
chsu_schedule_api/types/base.py
chsu_schedule_api/types/building.py
chsu_schedule_api/types/department.py
chsu_schedule_api/types/discipline.py
chsu_schedule_api/types/student_group.py
chsu_schedule_api/types/teacher.py
chsu_schedule_api/types/timetable.py
LICENSE
chsu_schedule_api-1.2.2.dist-info/LICENSE
chsu_schedule_api-1.2.2.dist-info/METADATA
chsu_schedule_api-1.2.2.dist-info/WHEEL
chsu_schedule_api-1.2.2.dist-info/RECORD
