Metadata-Version: 2.1
Name: chsu_schedule_api
Version: 1.2.2
Summary: Asynchronous API wrapper for CHSU schedule API
Home-page: https://github.com/vovchic17/CHSUScheduleAPI
License: MIT
Keywords: chsu,schedule,api
Author: VoVcHiC
Author-email: hello@chsutech.ru
Requires-Python: >=3.12,<4.0
Classifier: License :: OSI Approved :: MIT License
Classifier: Programming Language :: Python :: 3
Classifier: Programming Language :: Python :: 3.12
Requires-Dist: aiohttp (>=3.9.3,<4.0.0)
Requires-Dist: pydantic (>=2.6.3,<3.0.0)
Project-URL: Repository, https://github.com/vovchic17/CHSUScheduleAPI
